tiempo_deshima/Atmosphere/use_aris.py
tiempo_deshima/DESHIMA/MKID/filterbank.py
tiempo_deshima/DESHIMA/MKID/photon_noise.py
tiempo_deshima/DESHIMA/MKID/timeSigBoost.pyx
tiempo_deshima/DESHIMA/desim/README.md
tiempo_deshima/DESHIMA/desim/data/atm.csv
tiempo_deshima/DESHIMA/desim/data/plot_data_recal.csv
tiempo_deshima/DESHIMA/desim/data/z_Dl.csv
tiempo_deshima/DESHIMA/desim/environment.yml
tiempo_deshima/DESHIMA/desim/lines/Dl_at_z2.py
tiempo_deshima/DESHIMA/desim/lines/lineflux.py
tiempo_deshima/DESHIMA/desim/minidesim.py
tiempo_deshima/DESHIMA/use_desim.py
tiempo_deshima/Data/eta_atm/eta_atm.txt
tiempo_deshima/Data/splines_Tb_sky/spline_220.0GHz.npy
tiempo_deshima/Data/splines_Tb_sky/spline_220.4GHz.npy
tiempo_deshima/Data/splines_Tb_sky/spline_220.6GHz.npy
tiempo_deshima/Data/splines_Tb_sky/spline_220.9GHz.npy
tiempo_deshima/Data/splines_Tb_sky/spline_221.3GHz.npy
tiempo_deshima/Data/splines_Tb_sky/spline_221.8GHz.npy
tiempo_deshima/Data/splines_Tb_sky/spline_221.9GHz.npy
tiempo_deshima/Data/splines_Tb_sky/spline_222.2GHz.npy
tiempo_deshima/Data/splines_Tb_sky/spline_222.5GHz.npy
tiempo_deshima/Data/splines_Tb_sky/spline_222.7GHz.npy
tiempo_deshima/Data/splines_Tb_sky/spline_223.1GHz.npy
tiempo_deshima/Data/splines_Tb_sky/spline_223.2GHz.npy
tiempo_deshima/Data/splines_Tb_sky/spline_223.5GHz.npy
tiempo_deshima/Data/splines_Tb_sky/spline_223.8GHz.npy
tiempo_deshima/Data/splines_Tb_sky/spline_224.0GHz.npy
tiempo_deshima/Data/splines_Tb_sky/spline_224.4GHz.npy
tiempo_deshima/Data/splines_Tb_sky/spline_224.9GHz.npy
tiempo_deshima/Data/splines_Tb_sky/spline_225.0GHz.npy
tiempo_deshima/Data/splines_Tb_sky/spline_225.1GHz.npy
tiempo_deshima/Data/splines_Tb_sky/spline_225.3GHz.npy
tiempo_deshima/Data/splines_Tb_sky/spline_225.7GHz.npy
tiempo_deshima/Data/splines_Tb_sky/spline_225.8GHz.npy
tiempo_deshima/Data/splines_Tb_sky/spline_226.2GHz.npy
tiempo_deshima/Data/splines_Tb_sky/spline_226.3GHz.npy
tiempo_deshima/Data/splines_Tb_sky/spline_226.7GHz.npy
tiempo_deshima-0.1.17.dist-info/LICENSE
tiempo_deshima-0.1.17.dist-info/WHEEL
tiempo_deshima-0.1.17.dist-info/METADATA
tiempo_deshima-0.1.17.dist-info/RECORD
