Metadata-Version: 2.1
Name: tiempo-deshima
Version: 0.1.17
Summary: time-dependent end-to-end model for post-process optimization
Home-page: https://github.com/deshima-dev/tiempo_deshima
License: MIT
Author: Esmee Huijten
Maintainer: Stefanie Brackenhoff
Maintainer-email: s.a.brackenhoff@student.tudelft.nl
Requires-Python: >=3.7,<4.0
Classifier: License :: OSI Approved :: MIT License
Classifier: Programming Language :: Python :: 3
Classifier: Programming Language :: Python :: 3.7
Classifier: Programming Language :: Python :: 3.8
Classifier: Programming Language :: Python :: 3.9
Requires-Dist: astropy (>=4.0.1,<5.0.0)
Requires-Dist: galspec (>=0.2.5,<0.3.0)
Requires-Dist: joblib (>=0.16.0,<0.17.0)
Requires-Dist: matplotlib (>=3.3.2,<4.0.0)
Requires-Dist: numpy (>=1.19.2,<2.0.0)
Requires-Dist: pandas (>=1.1.2,<2.0.0)
Requires-Dist: pathlib (>=1.0.1,<2.0.0)
Requires-Dist: pydata_sphinx_theme (>=0.4.0,<0.5.0)
Requires-Dist: scipy (>=1.5.2,<2.0.0)
